CHANGES.rst
LICENSE.txt
MANIFEST.in
README.rst
setup.py
docs/Makefile
docs/__init__.py
docs/__init__.pyc
docs/conf.py
docs/index.rst
docs/requirements.txt
docs/_images/screen.png
docs/api/bottle_gui.rst
src/bottle_gui/__init__.py
src/bottle_gui/bottle_gui.py
src/bottle_gui.egg-info/PKG-INFO
src/bottle_gui.egg-info/SOURCES.txt
src/bottle_gui.egg-info/dependency_links.txt
src/bottle_gui.egg-info/not-zip-safe
src/bottle_gui.egg-info/requires.txt
src/bottle_gui.egg-info/top_level.txt
src/bottle_gui/static/style.css
src/bottle_gui/static/templates/descr.html
src/bottle_gui/static/templates/index.html
src/bottle_gui/static/templates/row.html
src/bottle_gui/static/templates/table.html
tests/test_gui.py
tests/services/__init__.py
tests/services/hist.py
tests/services/xex.py