Metadata-Version: 1.1
Name: bottle-gui
Version: 0.2.1
Summary: Package used to vizualize services in Bottle web framework.
Home-page: https://github.com/Bystroushaak/bottle-gui
Author: Bystroushaak
Author-email: bystrousak@kitakitsune.org
License: MIT
Platform: UNKNOWN
Classifier: Framework :: Bottle
Classifier: Topic :: Internet :: WWW/HTTP :: WSGI
Classifier: Topic :: Internet :: WWW/HTTP :: WSGI :: Application
Classifier: Topic :: Software Development :: Libraries
Classifier: Programming Language :: Python :: 2.7
Classifier: License :: OSI Approved :: MIT License
